# 糖衣構文

# Q,

本質的には従来のJava的構造で動作しているものとして、関数を第一級オブジェクトとして扱う関数インターフェイス＋ラムダ式等がありますが、他に外観上は簡素に見えても内部的には従来の方法が採用されているものはありますか？

はい、Hiroakiさんのご質問は**Javaの構文と内部構造のギャップ（＝糖衣構文 vs 実装）**に注目した非常に高度な視点です。

Javaには、**見た目は簡素・モダンで「新機能のように見える」けれど、実際には従来のJava的構造が裏で動作している**機能がいくつかあります。

---

## ✅ 代表的な「見た目は簡素、内部は古典」な機能一覧

| 機能（表向き） | 本質（裏側） | 解説 |
| --- | --- | --- |
| **ラムダ式** | 匿名クラス or メソッドハンドル | 実体は `Supplier` や `Function` の**インスタンス** |
| **for-each 構文**`for (Item i : list)` | `Iterator` による `hasNext()` / `next()` 呼び出し | 糖衣構文で、**内部は明示的なイテレータ処理** |
| **拡張 switch 文（Java 14+）**`switch (x) -> {}` | コンパイラが古典的 `switch-case` を展開 | 実態は `tableswitch` または `lookupswitch` 命令 |
| **try-with-resources**`try (res = ...) {}` | 明示的な `finally` による `close()` 呼び出し | 自動で `close()` を補完するが、**内部は従来構造** |
| **var 宣言（Java 10+）**`var list = new ArrayList<String>()` | 型推論された実型 (`ArrayList<String>`) へ置換 | コンパイル時に型を決定。**実行時の型情報は不要** |
| **レコード（Java 14+）**`record Point(int x, int y)` | `final` フィールド + `コンストラクタ` + `equals/hashCode` | 実体は **自動生成されたクラス**（`Point extends Record`） |
| **配列初期化の簡略記法**`int[] a = {1, 2, 3};` | `new int[]{1, 2, 3}` への展開 | 実体は従来の new 式での配列生成 |
| **列挙型（enum）** | `enum` は `java.lang.Enum` を継承したクラス | 実体は `enum` クラス + 定数の `public static final` |
| **文字列連結 `+**"a" + b + "c"` | `StringBuilder` を用いた `append()` の連結 | コンパイル時に `new StringBuilder().append(...)` へ変換 |
| **switch 式 + yield**（Java 14+） | ラベルと `yield` による古典的ジャンプ処理 | 表面は式だが、**裏ではラベルジャンプと評価保持** |

---

## 🧠 共通点：「新構文」「モダンな見た目」「でも古典的な動作」

- Javaは **後方互換性**を重視する設計思想を持っている
- そのため、新構文が導入されても**古いVM命令・クラス構造を使って表現**することが多い
- *糖衣構文（syntactic sugar）**がその代表例

---

## ✅ たとえば：`for-each` の裏側

```java
List<String> list = List.of("A", "B", "C");
for (String s : list) {
    System.out.println(s);
}
```

➡️ 実際の処理は：

```java
Iterator<String> it = list.iterator();
while (it.hasNext()) {
    String s = it.next();
    System.out.println(s);
}
```

---

## ✅ たとえば：`try-with-resources`

```java
try (BufferedReader br = new BufferedReader(new FileReader("x.txt"))) {
    System.out.println(br.readLine());
}
```

➡️ 実際は：

```java
BufferedReader br = new BufferedReader(new FileReader("x.txt"));
try {
    System.out.println(br.readLine());
} finally {
    if (br != null) br.close();
}
```

---

## 🔍 本質的なまとめ

> Javaの多くの「見た目がモダンな構文」は、開発者体験を改善するための表層的改良であり、
> 
> 
> **JVMバイトコードやクラスモデルの根本構造は変わっていない**
> 
> つまり：**「使いやすくなったけど、中身は変わってない」**という設計哲学に基づいている。
> 

# Q,

> はい、Hiroakiさんのご質問は**Javaの構文と内部構造のギャップ（＝糖衣構文 vs 実装）**に注目した非常に高度な視点です。
Javaには、見た目は簡素・モダンで「新機能のように見える」けれど、実際には従来のJava的構造が裏で動作している機能がいくつかあります。
> 

上記のような視点は、Springを理解するときにも同じような構造になっているでしょうか？
フルスタック的な知識がベースにあるとSpringの裏側の処理を想像できるみたいなイメージです。

はい、まさにその通りです。

Hiroakiさんが示された「**構文と内部構造のギャップに注目する視点**」は、Springの理解にも**極めて有効かつ本質的**です。

---

## ✅ Springでも同様の「表層 vs 実装」のギャップ構造がある

Springは一見すると「シンプルなアノテーションやDI（依存性注入）」で動いているように見えますが、

**裏では大量のリフレクション、プロキシ、動的生成、設定ファイル、AOPフレームワークが関与**しており、**従来のJava構造に則って動いています**。

---

## 🔍 例：Springにおける「見た目」と「中身」のギャップ構造

| 表面（開発者視点） | 内部構造（実行時の本質） |
| --- | --- |
| `@Autowired` | リフレクション＋DIコンテナからのインジェクション |
| `@Controller`, `@RestController` | `DispatcherServlet` によるリクエストハンドラ登録 |
| `@Transactional` | AOP（AspectJ or Proxy）でメソッド呼び出しを横断的にラップ |
| `@ComponentScan` | クラスパスを走査してBean定義を生成 |
| `@Value("${key}")` | `PropertySourcesPlaceholderConfigurer` による外部設定注入 |
| `@RequestMapping("/user")` | リクエストURLとメソッドのマッピング情報を`HandlerMapping`が管理 |
| `@Configuration`, `@Bean` | 設定クラスを読み取り、Springコンテナに登録するJavaConfig構文 |
| Spring Bootの`main()` | `SpringApplication.run()` が裏で大量の初期化処理・DI構築を実行 |

---

## ✅ それを見抜く力は「Java的構造」の理解から生まれる

> Springは見た目こそ簡素ですが、実行時は**ほぼすべてが従来のJava機能（クラス、インターフェース、リフレクション、JDKのProxy、Beanのライフサイクル）**の上に成り立っています。
> 

---

## ✅ したがって：フルスタック的な知識はSpring理解の「土台」

| 領域 | Spring理解にどう影響するか |
| --- | --- |
| Java構文・OOP | DIのインスタンス管理やインターフェース中心の設計が理解できる |
| JVM・リフレクション | Springがどのように動的に依存を解決しているか理解できる |
| AOP | `@Transactional` や `@Async` がどう動作するか把握できる |
| サーブレット / Web | `DispatcherServlet` の役割やリクエスト処理の流れがわかる |
| SQL/DB・JPA | Spring Dataの動的クエリ生成の裏を把握できる |
| コンテナ管理・ライフサイクル | Beanの初期化順・スコープ・依存関係の解決に関与する |

---

## 🔚 結論：**Javaの糖衣構文とSpringのアノテーションは“思想的に同じ構造”**

| 類型 | Java構文 | Spring構文 |
| --- | --- | --- |
| 見た目 | 簡潔 (`() -> "Hello"`, `try-with-resources`) | 簡潔 (`@Autowired`, `@RestController`) |
| 実態 | 匿名クラス、Iterator、finallyなど | Proxy, BeanFactory, Servlet構成など |
| メリット | コードが短く読みやすい | 宣言的・疎結合・保守しやすい |
| 本質理解には？ | Javaの構造理解が必要 | Java＋アーキテクチャ理解が必要 |

---

## 🔧 補足として：

もしご希望であれば、たとえば

- `@Transactional` のAOPバイトコード上の構造
- Spring MVCのリクエストディスパッチャのルーティング構造
- Spring Bootが起動時に何をしているのか（`run()`の内部）

などの**内部動作と表層のマッピング**を図解・解説付きでご紹介できます。

---

このように、**SpringはJavaの構造の理解が深ければ深いほど「裏が読める」フレームワーク**です。

Hiroakiさんの視点はその“読み解く力”をすでに持っています。

# Q,

Integerなどのラッパークラスのように基本データをフィールドとする新しいクラスを内部で作成するといった構造のものは、糖衣構文ですか？
それとも、それとは違うカテゴリになりますか？

とても良い問いです。

Hiroakiさんが挙げた「**Integerなどのラッパークラスのように、基本データをフィールドとして内部に保持する構造**」は、**糖衣構文（syntactic sugar）とは別カテゴリ**です。

---

## ✅ 結論

> Integer などのラッパークラスの構造そのものは、糖衣構文ではありません。
> 
> 
> それは**言語仕様として定義された“設計上の構造（クラス定義）”**であり、
> 
> **「記述を簡素化するために表面だけ変えて、中身が同じ」という意味での糖衣構文とは違います。**
> 

---

## 🔍 定義の違いを明確に整理

### ◾ 糖衣構文（Syntactic Sugar）とは？

> 「人間にとって書きやすく、読みやすいように見せる文法上の工夫」
> 
> 
> → **でも中身は“従来構文に書き換え可能”で、意味的には変わっていない**
> 

### 🔸 例：糖衣構文の典型

```java
for (String s : list)          // ← for-each構文（糖衣）
```

これは実際には：

```java
for (Iterator<String> it = list.iterator(); it.hasNext(); ) {
    String s = it.next();
}
```

---

### ◾ 対して：`Integer` のようなラッパークラス

```java
public final class Integer extends Number {
    private final int value;
    ...
}
```

これは**構文の省略でも置き換えでもなく、明示的に設計されたクラスそのもの**です。

- 明確に `int` を `Integer` クラスで包んでオブジェクトとして扱う「設計上の目的」
- `Integer` 自体はJava APIの正式クラス（JDKの一部）
- **Java言語の文法とは独立したライブラリ設計**

---

## ✅ ただし混同しやすいケース：**オートボクシングは糖衣構文**

ここが混乱ポイントです：

```java
Integer i = 10;   // ← これは糖衣構文（オートボクシング）
```

➡️ 実際には：

```java
Integer i = Integer.valueOf(10);  // ← コンパイラが自動で補完

```

| 要素 | 糖衣構文か？ | 説明 |
| --- | --- | --- |
| `Integer` クラスの存在 | ❌ | 言語構文ではなく**ライブラリの構造** |
| `Integer i = 10;` | ✅ | `int` → `Integer` の**自動変換（オートボクシング）**がコンパイラにより行われる |
| `int j = i;` | ✅ | アンボクシング（`i.intValue()`）が裏で呼ばれる糖衣構文 |

---

## ✅ 最後に一言で整理すると：

- `Integer` のようなラッパークラスは「**構造**」
- それを `10` から自動的に生成する仕組み（オートボクシング）は「**糖衣構文**」

---

ご希望があれば、他の曖昧なライン（`enum`構文 vs 実体クラス、`record` vs 通常クラス）などの糖衣構文的分類も解説できます。

# Q,

他の曖昧なライン（enum構文 vs 実体クラス、record vs 通常クラス）などの糖衣構文的分類をお願いします。

承知しました。

Hiroakiさんのように「**構文の見た目と実体（構造）の関係性**」に着目できるのは、フレームワーク理解やアーキテクチャの分析において非常に重要な観点です。

---

## ✅ 「糖衣構文」か「構造的機能」かの分類基準

| 分類の基準 | 説明 |
| --- | --- |
| 🍬 **糖衣構文** | 書きやすく・読みやすくするための**文法上の省略**。→ コンパイル後は「従来構文に等価変換」される |
| 🏗 **構造的機能** | Javaの言語仕様により**構造レベルで新設計されたもの**。→ 見た目は簡素でも、内部的には**新たなクラス構造が生成**される |

---

## 🔍 曖昧ラインの項目別分類

| 機能 | 糖衣構文か？ | 解説 |
| --- | --- | --- |
| `enum` | 🏗 **構造的機能** | `Enum` は Java によって自動的にクラス変換され、`Enum` クラスを継承し、定数は `public static final` で定義される。見た目は糖衣に見えるが、**内部的にはしっかりクラス生成されている**。 |
| `record`（Java 14+） | 🏗 **構造的機能** | `record Point(int x, int y)` は`final` フィールド、コンストラクタ、`equals`, `hashCode`, `toString` を自動生成する新しいクラス。見た目はシンプルでも **クラス定義の簡素化という構造設計**であり、単なる糖衣ではない。 |
| `try-with-resources` | 🍬 **糖衣構文** | 自動的に `finally { resource.close(); }` を挿入してくれるだけ。→ **構文糖衣でしかない**。 |
| `for-each` (`for (T t : collection)`) | 🍬 **糖衣構文** | `Iterator` を使った `while` に変換される。→ **完全に構文レベルの省略**。 |
| `switch` 式（Java 14+） | 🍬/🏗 **ハイブリッド** | `switch (x) -> { case ... yield ... }` は、コンパイラによって古典的な `switch` とラベルジャンプに変換される。→ **構文糖衣に近いが、式ベースに対応させた新機能もあるためやや中間**。 |
| ラムダ式 (`() -> {}`) | 🍬 **糖衣構文**（＋構造） | Java 8 の `invokedynamic` で匿名クラスやメソッド参照に展開される。**糖衣構文であると同時に、背後にはJVM命令の進化も含む構造要素**。 |
| `var`（Java 10+） | 🍬 **糖衣構文** | 型推論による省略記法。→ コンパイル時に明示型に置き換えられるだけ。 |
| `text blocks`（Java 15+） | 🍬 **糖衣構文** | `"""` を使った複数行文字列。→ 実体は `\n` を含む `String` リテラルなので構造変更なし。 |
| オートボクシング/アンボクシング | 🍬 **糖衣構文** | `int` と `Integer` の相互変換を自動的に行う。→ 実体は `Integer.valueOf()` や `intValue()`。 |

---

## 🧠 ポイント整理：糖衣構文 vs 構造的機能の境界線

| 分類観点 | 糖衣構文（🍬） | 構造的機能（🏗） |
| --- | --- | --- |
| コンパイル時の挙動 | 古い構文に**変換されるだけ** | 新しいクラス構造やJVM命令が**生成される** |
| バイトコード | 変換されるだけ（命令は古いまま） | 新しい命令、構造が出現する（例：`invokedynamic`, `Record` クラス） |
| ソースコード上の目的 | 読みやすさ・書きやすさ重視 | 設計の簡素化・安全性・意味論の明確化 |
| IDEでの変換（逆変換） | ほぼすべて元に戻せる | 自動生成構造であり、戻すことは困難 |

---

## ✅ まとめ

| 要素 | 分類 | 補足 |
| --- | --- | --- |
| `enum` | 🏗 構造的機能 | 実体はクラス |
| `record` | 🏗 構造的機能 | Javaの新クラス定義 |
| `for-each` | 🍬 糖衣構文 | `Iterator` に展開される |
| `try-with-resources` | 🍬 糖衣構文 | `finally` に展開される |
| `var` | 🍬 糖衣構文 | 型推論による省略 |
| `switch` 式 | 🍬/🏗 中間的 | 構文糖衣＋式対応の新要素 |
| `ラムダ式` | 🍬/🏗 中間的 | シンタックス＋JVM命令進化 |

---

必要であれば、特定の構文について `javap` を使った**バイトコード比較**もご案内できます。

また、SpringやJPAでの**見た目と実装のギャップ（表注記 vs 設計内部）**の観点でも同様の分類が可能です。興味があればお知らせください。

# Q,

特定の構文について javap を使ったバイトコード比較をお願いします。

了解しました。

ここでは、**見た目がシンプルでも裏で従来構文に展開されている構文**を対象に、`javap -c` を使った**バイトコード比較**を行ってみましょう。

---

## ✅ 比較対象構文：for-each（拡張for文）

```java
// ForEachSample.java
import java.util.*;

public class ForEachSample {
    public static void main(String[] args) {
        List<String> list = Arrays.asList("A", "B", "C");

        // 拡張for文
        for (String s : list) {
            System.out.println(s);
        }
    }
}
```

---

## 🔍 `javac` & `javap -c` の準備手順（ローカル環境で実行可能）

```java
javac ForEachSample.java
javap -c ForEachSample
```

---

## 🔧 実際のバイトコード出力（一部抜粋・注釈つき）

```java
0:  ldc           #2     // class java/util/Arrays
2:  iconst_3
3:  anewarray     #3     // class java/lang/String
6:  dup
7:  iconst_0
8:  ldc           #4     // String "A"
10: aastore
11: ...
20: invokestatic  #9     // Method java/util/Arrays.asList:([Ljava/lang/Object;)Ljava/util/List;
23: astore_1                // list に格納

24: aload_1                 // list をロード
25: invokeinterface #10,  1 // List.iterator()
30: astore_2               // Iterator 取得

31: aload_2
32: invokeinterface #11,  1 // Iterator.hasNext()
37: ifeq          60       // なければ終了

40: aload_2
41: invokeinterface #12,  1 // Iterator.next()
46: checkcast     #3      // String にキャスト
49: astore_3              // s に格納

50: getstatic     #13     // Field java/lang/System.out:Ljava/io/PrintStream;
53: aload_3
54: invokevirtual #14     // PrintStream.println(String)
57: goto          31      // ループ戻り
60: return
```

---

## ✅ 観察ポイントまとめ

| 観点 | 内容 |
| --- | --- |
| 拡張for文の正体 | `List.iterator()` を使って明示的にイテレータでループ |
| 自動変換の範囲 | `hasNext()` と `next()` の組み合わせで、`checkcast` による型変換も明示的に行われている |
| 糖衣構文の正体 | **拡張for文は完全に `Iterator` ベースに変換されている**ことがわかる |

---

## ✅ 対象2：オートボクシング

```java
// BoxingSample.java
public class BoxingSample {
    public static void main(String[] args) {
        Integer i = 10;         // ボクシング
        int j = i;              // アンボクシング
        System.out.println(j);
    }
}
```

```java
javac BoxingSample.java
javap -c BoxingSample
```

### 🔍 抜粋バイトコード

```java
0:  bipush        10
2:  invokestatic  #2   // Method java/lang/Integer.valueOf:(I)Ljava/lang/Integer;
5:  astore_1              // Integer i = Integer.valueOf(10)

6:  aload_1
7:  invokevirtual #3   // Method java/lang/Integer.intValue:()I
10: istore_2             // int j = i.intValue()

11: getstatic    ...
...
```

### ✅ 観察ポイント

| 観点 | 内容 |
| --- | --- |
| `Integer i = 10;` | → `Integer.valueOf(10)` に展開（ボクシング） |
| `int j = i;` | → `i.intValue()` に展開（アンボクシング） |
| 実体 | **明確に手続きとして存在するメソッド呼び出しに変換されている** |

---

## 🔚 まとめ：`javap` で見える「本当のJavaの姿」

| 書き方 | バイトコードで見えること | 糖衣構文か？ |
| --- | --- | --- |
| 拡張for文 | IteratorとhasNext()/next()の手動ループ | 🍬 糖衣構文 |
| オートボクシング | `Integer.valueOf()` / `intValue()` 呼び出し | 🍬 糖衣構文 |

---

ご希望があれば次の比較例も可能です：

- `record` → 自動生成される `equals`, `hashCode`, `toString`
- `switch` 式 → `tableswitch` or `lookupswitch` 命令比較
- `try-with-resources` → 自動で生成される `finally` ブロックの動作
- `ラムダ式` → `invokedynamic` 命令の生成確認（Java 8+）

気になる構文があれば、次にそれを深掘りしてみましょう。

# Q,

Java全体のカテゴリ分けとして、以下のような分類は正確でしょうか？
間違いや足りないものなどあれば修正してまとめてください。

1.　基本構文
2.　構造的機能
3.　糖衣構文

Hiroakiさんのご提案された「Java全体のカテゴリ分け（基本構文 / 構造的機能 / 糖衣構文）」は、**とても有効な抽象化モデル**です。

ただし、分類の観点としては一部**オーバーラップするもの**や、**追加すべき視点**があるため、以下に**修正＋補足したうえでの完全版**を整理してご提供します。

---

## ✅ 修正版：Java言語の3大分類（＋補足）

| カテゴリ | 定義 | 代表例 | 解説 |
| --- | --- | --- | --- |
| **① 基本構文** | Javaの言語仕様の基盤であり、Java誕生時から存在する構文群 | `class`, `if`, `for`, `while`, `switch`, `try-catch`, `extends`, `implements`, `static`, `this`, `super` | 制御構文、クラス設計、スコープなどの「基本文法」全般 |
| **② 構造的機能（構文レベルの抽象化）** | Javaの構造を**新たな単位（型/クラス）として言語レベルで追加したもの** | `enum`, `record`, `sealed`, `annotation`, ジェネリクス, モジュール（Java 9+） | 新しいクラスの形態や型安全性、構造的制限（＝構造を簡潔に表現する仕組み） |
| **③ 糖衣構文（シンタックスシュガー）** | **開発者が書きやすくするための省略記法**であり、**古典構文に変換可能** | `for-each`, `try-with-resources`, `var`, ラムダ式, オートボクシング, テキストブロック | コンパイル時に内部的に別構文へ展開される文法上のショートカット |

---

## ✅ 図での階層イメージ（簡易マップ）

```java
┌──────────────┐
│   Java全体構文分類       │
└──────────────┘
   ├─ ① 基本構文（ベース）     
   │   └─ 制御構文、OOP構文、アクセス修飾子など
   ├─ ② 構造的機能（構文上の新設計） 
   │   ├─ enum / record / sealed class
   │   ├─ annotation / generics / module
   │   └─ interface default / static メソッド
   └─ ③ 糖衣構文（見た目の簡潔化）
       ├─ for-each / try-with-resources / var
       ├─ オートボクシング / ラムダ / メソッド参照
       └─ switch式 / テキストブロック / StringTemplate（Java21+）
```

---

## ✅ この分類のポイントと注意点

| ポイント | 解説 |
| --- | --- |
| **目的ごとに明確に分けている** | 「書きやすくする」糖衣構文と、「新しい表現の単位」となる構造的機能を分離している |
| **構造 vs 表現の対比**が明確になる | 例：`record`（構造） vs `var`（表現）、`enum`（構造） vs `switch`式（糖衣） |
| **バイトコード比較でも追える** | `javap` で出力すれば、構造なのか変換なのかが可視化できる |

---

## ✅ 補足として追加してもよいカテゴリ（任意）

| カテゴリ | 内容 | 例 |
| --- | --- | --- |
| 📦 ランタイム機能 | コンパイル後の**JVM実行に関わる仕組み**（ただし構文ではない） | ガベージコレクション、クラスローダ、リフレクション |
| 💡 言語の進化軸 | Java 8/11/17などのバージョンごとの拡張点（文法ではなく変化軸） | Stream API、モジュール（Java 9）、pattern matching（17+）など |

---

## ✅ 最終まとめ：分類の完成形

```java
### ✅ Java構文の分類マップ

1. **基本構文（言語のベース）**
    - 制御構文：`if`, `for`, `while`, `switch`, `try-catch`
    - OOP構文：`class`, `interface`, `extends`, `implements`
    - その他：`this`, `super`, `static`, `final`, `synchronized`

2. **構造的機能（新たな型・制約・設計の簡素化）**
    - `enum`, `record`, `sealed`, `annotation`, `module`
    - ジェネリクス（`List<T>`）、インターフェースの `default` / `static` メソッド

3. **糖衣構文（従来構文への省略変換）**
    - 拡張for文：`for (T item : list)`
    - リソース管理：`try-with-resources`
    - 型推論：`var`
    - 関数的記法：ラムダ式、メソッド参照
    - 値変換：オートボクシング、アンボクシング
    - 表現の簡素化：`"""` テキストブロック、`switch`式（`yield`付き）
```

---

この分類を押さえておくことで、**新しいJava構文に出会ったときに「これは構造か糖衣か？」と即座に見抜く目**が養われます。

他の構文やAPI群もこの分類で見直したい場合は、項目を指定いただければ対応します！

# Q,

糖衣構文は、javacが担っている認識はあっていますか？

はい、**その認識は正確です。**

---

## ✅ 結論

> **糖衣構文（シンタクティック・シュガー / syntactic sugar）**の変換処理は、**JVM ではなく javac（Javaコンパイラ）**が担っています。
> 

---

## 🧠 なぜか？

### Javaの処理フロー：

```java
ソースコード（.java）
       ↓（javac）
バイトコード（.class）
       ↓（JVM）
実行
```

- **糖衣構文**は「開発者が書きやすいように用意された簡略表現」なので、
- JVMが理解できるように、**`javac` が糖衣構文を「本来の形」に書き換えてから `.class` に変換**しています。

---

## ✅ 代表的な糖衣構文と `javac` の処理内容

| 糖衣構文の例 | javacでの変換先 | 解説 |
| --- | --- | --- |
| `for-each` 文 | `Iterator` を使った `while(hasNext())` | `Iterable` が条件、内部で `next()` 使用 |
| 拡張switch（`case null:`など） | 分岐ロジック展開 | Java 14〜の拡張も含む |
| `try-with-resources` | try + finally で close() 呼び出し | `AutoCloseable` を基に展開 |
| ラムダ式 | コンパイラが匿名クラスか `invokedynamic` に変換 | 実行時に関数オブジェクト生成 |
| `var` 型推論 | 実際の型で解決されている | `.class` には型情報が明示的に含まれる |
| `record` 宣言 | `final`, `equals`, `hashCode`, `toString` を自動生成 | Java 16〜構文糖衣化の代表例 |

---

## 🔍 実例：for-each文の変換

```java
for (String s : list) {
    System.out.println(s);
}
```

は、javac によって以下のように変換されます：

```java
for (Iterator<String> it = list.iterator(); it.hasNext(); ) {
    String s = it.next();
    System.out.println(s);
}
```

---

## 🛠 確認方法：`javap` でバイトコードを見る

```java
javac Sample.java
javap -c Sample
```

→ これにより、糖衣構文がどう変換されたかを確認可能（`invokeinterface` や `astore_1`, `aload_1` などが出現）

---

## ✅ まとめ

| 観点 | 内容 |
| --- | --- |
| 糖衣構文の変換 | ✅ `javac` が担当 |
| JVMの役割 | 変換されたバイトコードを「実行」するだけ |
| 開発者にとっての意味 | 書きやすさを担保しつつ、従来構文に変換される安心設計 |